rougail/__init__.py
rougail/config.py
rougail/convert.py
rougail/error.py
rougail/i18n.py
rougail/object_model.py
rougail/tiramisu.py
rougail/tiramisureflector.py
rougail/utils.py
rougail/annotator/__init__.py
rougail/annotator/family.py
rougail/annotator/property.py
rougail/annotator/value.py
rougail/annotator/variable.py
rougail/locale/fr/LC_MESSAGES/rougail.mo
rougail/structural_commandline/annotator.py
rougail/structural_commandline/config.py
rougail/structural_commandline/object_model.py
rougail/update/__init__.py
rougail/update/update.py
rougail-1.1.1.dist-info/LICENSE
rougail-1.1.1.dist-info/WHEEL
rougail-1.1.1.dist-info/METADATA
rougail-1.1.1.dist-info/RECORD
