Metadata-Version: 2.1
Name: rougail
Version: 1.1.1
Summary: A consistency handling system that was initially designed in the configuration management
Author-email: Emmanuel Garette <gnunux@gnunux.info>
Requires-Python: >=3.8
Classifier: License :: OSI Approved :: GNU Library or Lesser General Public License (LGPL)
Classifier: Programming Language :: Python
Classifier: Programming Language :: Python :: 3.8
Classifier: Programming Language :: Python :: 3.9
Classifier: Programming Language :: Python :: 3.10
Classifier: Programming Language :: Python :: 3.11
Classifier: Programming Language :: Python :: 3.12
Classifier: Programming Language :: Python :: 3
Classifier: Operating System :: OS Independent
Classifier: Natural Language :: English
Classifier: Natural Language :: French
Requires-Dist: ruamel.yaml ~= 0.18.6
Requires-Dist: pydantic ~= 2.9.2
Requires-Dist: jinja2 ~= 3.1.4
Requires-Dist: tiramisu >=5.0,<6
Requires-Dist: pylint ~= 3.0.3 ; extra == "dev"
Requires-Dist: pytest ~= 8.2.2 ; extra == "dev"
Requires-Dist: lxml ~= 5.2.2 ; extra == "dev"
Project-URL: Home, https://forge.cloud.silique.fr/stove/rougail
Provides-Extra: dev
